freenrgworkflows-1.0.0.data/scripts/run_networkanalysis.py
freenrgworkflows-1.0.0.dist-info/DESCRIPTION.rst
freenrgworkflows-1.0.0.dist-info/METADATA
freenrgworkflows-1.0.0.dist-info/RECORD
freenrgworkflows-1.0.0.dist-info/WHEEL
freenrgworkflows-1.0.0.dist-info/metadata.json
freenrgworkflows-1.0.0.dist-info/top_level.txt
networkanalysis/__init__.py
networkanalysis/_version.py
networkanalysis/experiments.py
networkanalysis/jupyter.py
networkanalysis/networkanalysis.py
networkanalysis/plotting.py
networkanalysis/stats.py
