Metadata-Version: 2.0
Name: freenrgworkflows
Version: 1.0.0
Summary: python package for analysis relative free energy calculations with Sire
Home-page: https://github.com/michellab/freenrgworkflows
Maintainer: Antonia Mey
Maintainer-email: antonia.mey@ed.ac.uk
License: LGPLv3+
Keywords: relative free energy,perturbation network
Platform: UNKNOWN
Classifier: Development Status :: 3 - Alpha
Classifier: Environment :: Console
Classifier: Intended Audience :: Science/Research
Classifier: Natural Language :: English
Classifier: Operating System :: MacOS :: MacOS X
Classifier: Operating System :: POSIX :: Linux
Classifier: Programming Language :: Python :: 2.7
Classifier: Topic :: Scientific/Engineering :: Bio-Informatics
Classifier: Topic :: Scientific/Engineering :: Chemistry
Classifier: Topic :: Scientific/Engineering :: Mathematics
Classifier: Topic :: Scientific/Engineering :: Physics
